spdstrlib/__init__.py
spdstrlib/data.py
spdstrlib/read.py
spdstrlib/util.py
spdstrlib/write.py
spdstrlib-0.1.34.dist-info/LICENSE
spdstrlib-0.1.34.dist-info/WHEEL
spdstrlib-0.1.34.dist-info/METADATA
spdstrlib-0.1.34.dist-info/RECORD
