Metadata-Version: 2.1
Name: spdstrlib
Version: 0.1.34
Summary: Speedster application project library manager.
Author: Diogo André
Author-email: das.dias6@gmail.com
Requires-Python: >=3.9,<4.0
Classifier: Programming Language :: Python :: 3
Classifier: Programming Language :: Python :: 3.10
Classifier: Programming Language :: Python :: 3.9
Requires-Dist: loguru (>=0.6.0,<0.7.0)
